gladiator/__init__.py
gladiator/__main__.py
gladiator/generate/code.py
gladiator/generate/constants.py
gladiator/generate/templates.py
gladiator/mixins.py
gladiator/optional.py
gladiator/options.py
gladiator/parse/command.py
gladiator/parse/enum.py
gladiator/parse/extension.py
gladiator/parse/feature.py
gladiator/parse/type.py
gladiator/prepare/command.py
gladiator/prepare/enum.py
gladiator/prepare/feature.py
gladiator/prepare/resource_wrapper.py
gladiator/prepare/style.py
gladiator/resources/__init__.py
gladiator/resources/data/cpp_keywords
gladiator/resources/data/enum_name_overrides
gladiator/resources/data/enum_underlying_type_overrides
gladiator/resources/data/low_level_types
gladiator/resources/data/scoped_resources_multi
gladiator/resources/data/scoped_resources_single
gladiator/resources/data/type_translations
gladiator/resources/templates/_include/enable_bitmask_operators.hxx
gladiator/resources/templates/_include/khrplatform.hxx
gladiator/resources/templates/_include/opengl_debug.hxx
gladiator/resources/templates/_include/scoped_enum_bitfield.hxx
gladiator/resources/templates/_include/scoped_resource_global.hxx
gladiator/resources/templates/_include/type_safe_casts.hxx
gladiator/resources/templates/_util/command_wrapper.jinja2
gladiator/resources/templates/_util/conversion.jinja2
gladiator/resources/templates/_util/resolve.jinja2
gladiator/resources/templates/_util/type_reference.jinja2
gladiator/resources/templates/after.jinja2
gladiator/resources/templates/before.jinja2
gladiator/resources/templates/enum.jinja2
gladiator/resources/templates/enum_collection.jinja2
gladiator/resources/templates/loader/global.jinja2
gladiator/resources/templates/loader/object.jinja2
gladiator/resources/templates/loader.jinja2
gladiator/resources/templates/resource_wrapper/global.jinja2
gladiator/resources/templates/resource_wrappers.jinja2
gladiator/resources/templates/types.jinja2
gladiator/tools/compare.py
gladiator_gen-0.2.0.dist-info/LICENSE
gladiator_gen-0.2.0.dist-info/WHEEL
gladiator_gen-0.2.0.dist-info/METADATA
gladiator_gen-0.2.0.dist-info/RECORD
